docs/conf.py
pyyc/__init__.py
pyyc/__main__.py
pyyc/mod.py
pyyc/subpkgA/__init__.py
pyyc/subpkgA/modA1.py
pyyc/subpkgA/modA2.py
pyyc/subpkgB/__init__.py
pyyc/subpkgB/modB.py
tests/__init__.py
tests/test_mod.py
pyyc-1.0.dist-info/LICENSE
pyyc-1.0.dist-info/METADATA
pyyc-1.0.dist-info/WHEEL
pyyc-1.0.dist-info/entry_points.txt
pyyc-1.0.dist-info/top_level.txt
pyyc-1.0.dist-info/RECORD
