Metadata-Version: 2.1
Name: pyyc
Version: 1.0
Summary: Test package
Author-email: Yannick Copin <y.copin@ipnl.in2p3.fr>
License: BSD 3-Clause "New" or "Revised" License
Project-URL: Repository, https://gitlab.in2p3.fr/ycopin/pyyc
Project-URL: Documentation, https://ycopin.pages.in2p3.fr/pyyc/
Classifier: Development Status :: 1 - Planning
Classifier: Intended Audience :: Education
Classifier: License :: OSI Approved :: BSD License
Classifier: Programming Language :: Python :: 3
Classifier: Operating System :: OS Independent
Classifier: Topic :: Education
Requires-Python: >=3.6
License-File: LICENSE
Requires-Dist: importlib-resources ; python_version < "3.10"
Provides-Extra: docs
Requires-Dist: nbsphinx ; extra == 'docs'
Requires-Dist: ipython ; extra == 'docs'
Provides-Extra: tests
Requires-Dist: pytest ; extra == 'tests'
Requires-Dist: coverage ; extra == 'tests'
